phone_mcp_by_trae/__init__.py
phone_mcp_by_trae/__main__.py
phone_mcp_by_trae/phone_cli.py
phone_mcp_by_trae/phone_mcp.py
phone_mcp_by_trae-0.1.0.dist-info/METADATA
phone_mcp_by_trae-0.1.0.dist-info/WHEEL
phone_mcp_by_trae-0.1.0.dist-info/entry_points.txt
phone_mcp_by_trae-0.1.0.dist-info/top_level.txt
phone_mcp_by_trae-0.1.0.dist-info/RECORD
