Metadata-Version: 2.4
Name: phone-mcp-by-trae
Version: 0.1.0
Summary: 一个通过ADB命令控制Android手机的MCP插件
Home-page: https://github.com/hao-cyber/phone-mcp-by-trae
Author: Hao
Author-email: example@example.com
License: MIT
Project-URL: Bug Tracker, https://github.com/hao-cyber/phone-mcp/issues
Project-URL: Documentation, https://github.com/hao-cyber/phone-mcp
Project-URL: Source Code, https://github.com/hao-cyber/phone-mcp
Keywords: android,adb,mcp,phone,control
Classifier: Programming Language :: Python :: 3
Classifier: License :: OSI Approved :: MIT License
Classifier: Operating System :: OS Independent
Requires-Python: >=3.7
Requires-Dist: mcp
Dynamic: author
Dynamic: author-email
Dynamic: classifier
Dynamic: description
Dynamic: description-content-type
Dynamic: home-page
Dynamic: keywords
Dynamic: license
Dynamic: project-url
Dynamic: requires-dist
Dynamic: requires-python
Dynamic: summary
